xicam/Acquire/__init__.py
xicam/Acquire/runengine.py
xicam.Acquire-0.1.0.dist-info/METADATA
xicam.Acquire-0.1.0.dist-info/WHEEL
xicam.Acquire-0.1.0.dist-info/entry_points.txt
xicam.Acquire-0.1.0.dist-info/top_level.txt
xicam.Acquire-0.1.0.dist-info/RECORD
